odoo/addons/stock_move_line_change_lot/README.rst
odoo/addons/stock_move_line_change_lot/__init__.py
odoo/addons/stock_move_line_change_lot/__manifest__.py
odoo/addons/stock_move_line_change_lot/i18n/it.po
odoo/addons/stock_move_line_change_lot/i18n/stock_move_line_change_lot.pot
odoo/addons/stock_move_line_change_lot/models/__init__.py
odoo/addons/stock_move_line_change_lot/models/stock_move_line.py
odoo/addons/stock_move_line_change_lot/readme/CONTRIBUTORS.md
odoo/addons/stock_move_line_change_lot/readme/DESCRIPTION.md
odoo/addons/stock_move_line_change_lot/static/description/icon.png
odoo/addons/stock_move_line_change_lot/static/description/index.html
odoo/addons/stock_move_line_change_lot/tests/__init__.py
odoo/addons/stock_move_line_change_lot/tests/test_change_lot.py
odoo_addon_stock_move_line_change_lot-18.0.1.0.0.2.dist-info/METADATA
odoo_addon_stock_move_line_change_lot-18.0.1.0.0.2.dist-info/WHEEL
odoo_addon_stock_move_line_change_lot-18.0.1.0.0.2.dist-info/top_level.txt
odoo_addon_stock_move_line_change_lot-18.0.1.0.0.2.dist-info/RECORD
